skosprovider_oe/__init__.py
skosprovider_oe/providers.py
skosprovider_oe-0.5.0.dist-info/RECORD
skosprovider_oe-0.5.0.dist-info/WHEEL
skosprovider_oe-0.5.0.dist-info/METADATA
skosprovider_oe-0.5.0.dist-info/metadata.json
skosprovider_oe-0.5.0.dist-info/pbr.json
skosprovider_oe-0.5.0.dist-info/top_level.txt
skosprovider_oe-0.5.0.dist-info/DESCRIPTION.rst
