Metadata-Version: 2.0
Name: skosprovider-oe
Version: 0.5.0
Summary: A SKOS provider for OE vocabularies.
Home-page: http://github.com/koenedaele/skosprovider_oe
Author: Koen Van Daele
Author-email: koen_van_daele@telenet.be
License: MIT
Platform: UNKNOWN
Classifier: Development Status :: 4 - Beta
Classifier: Intended Audience :: Developers
Classifier: Natural Language :: English
Classifier: License :: OSI Approved :: MIT License
Classifier: Programming Language :: Python
Classifier: Programming Language :: Python :: 2.7
Classifier: Programming Language :: Python :: 3.3
Classifier: Programming Language :: Python :: 3.4
Classifier: Programming Language :: Python :: 3.5
Requires-Dist: skosprovider (>=0.6.0)
Requires-Dist: requests (>=1.0.0)
